long_weekends/__init__.py
long_weekends/long_weekends.py
long_weekends/test/__init__.py
long_weekends/test/unit/__init__.py
long_weekends/test/unit/test_long_weekends.py
python_long_weekends-0.1.1.dist-info/LICENSE
python_long_weekends-0.1.1.dist-info/METADATA
python_long_weekends-0.1.1.dist-info/WHEEL
python_long_weekends-0.1.1.dist-info/top_level.txt
python_long_weekends-0.1.1.dist-info/RECORD
