Metadata-Version: 2.1
Name: python-long-weekends
Version: 0.1.1
Summary: Spot holiday "bridges" and long weekends
Home-page: https://github.com/kryptonite0/python-long-weekends
Author: Giulia Savorgnan
Author-email: giulia.savorgnan@gmail.com
License: UNKNOWN
Project-URL: Bug Tracker, https://github.com/kryptonite0/python-long-weekends/issues
Platform: UNKNOWN
Classifier: Programming Language :: Python :: 3
Classifier: License :: OSI Approved :: MIT License
Classifier: Operating System :: OS Independent
Requires-Python: >=3.8
License-File: LICENSE
Requires-Dist: pandas (>=1.3.2)
